crew/__init__.py
crew/exceptions.py
crew/master/__init__.py
crew/master/threaded_client.py
crew/master/tornado/__init__.py
crew/master/tornado/adapter.py
crew/master/tornado/client.py
crew/master/tornado/multitask.py
crew/worker/__init__.py
crew/worker/context.py
crew/worker/handler.py
crew/worker/listener.py
crew/worker/pubsub.py
crew/worker/run.py
crew/worker/task.py
crew/worker/thread.py
crew-0.9.0.dist-info/DESCRIPTION.rst
crew-0.9.0.dist-info/METADATA
crew-0.9.0.dist-info/RECORD
crew-0.9.0.dist-info/WHEEL
crew-0.9.0.dist-info/metadata.json
crew-0.9.0.dist-info/top_level.txt
