Metadata-Version: 2.0
Name: crew
Version: 0.9.0
Summary: AMQP based worker/master pattern framework
Home-page: http://github.com/mosquito/crew
Author: Dmitry Orlov <me@mosquito.su>
Author-email: me@mosquito.su
License: MIT
Platform: all
Classifier: Environment :: Console
Classifier: Programming Language :: Python
Requires-Dist: pika
Requires-Dist: shortuuid
